odoo/addons/l10n_ch_states/README.rst
odoo/addons/l10n_ch_states/__init__.py
odoo/addons/l10n_ch_states/__manifest__.py
odoo/addons/l10n_ch_states/data/res_country_states.xml
odoo/addons/l10n_ch_states/i18n/de.po
odoo/addons/l10n_ch_states/i18n/fr.po
odoo/addons/l10n_ch_states/i18n/it.po
odoo/addons/l10n_ch_states/i18n/l10n_ch_states.pot
odoo/addons/l10n_ch_states/i18n/nb_NO.po
odoo/addons/l10n_ch_states/models/__init__.py
odoo/addons/l10n_ch_states/models/res_country.py
odoo11_addon_l10n_ch_states-11.0.1.0.0.dist-info/DESCRIPTION.rst
odoo11_addon_l10n_ch_states-11.0.1.0.0.dist-info/METADATA
odoo11_addon_l10n_ch_states-11.0.1.0.0.dist-info/RECORD
odoo11_addon_l10n_ch_states-11.0.1.0.0.dist-info/WHEEL
odoo11_addon_l10n_ch_states-11.0.1.0.0.dist-info/metadata.json
odoo11_addon_l10n_ch_states-11.0.1.0.0.dist-info/top_level.txt
